Metadata-Version: 2.1
Name: ar-one-qdk-web
Version: 0.0.7
Summary: UNKNOWN
Author: PunchyArchy
Author-email: ksmdrmvscthny@gmail.com
License: UNKNOWN
Platform: UNKNOWN
License-File: LICENSE
Requires-Dist: qodex-dk
